stardive/__init__.py
stardive/adapters/__init__.py
stardive/artifacts/__init__.py
stardive/artifacts/enums.py
stardive/artifacts/serializer.py
stardive/artifacts/storage.py
stardive/cli/__init__.py
stardive/execution/__init__.py
stardive/execution/execute.py
stardive/execution/types.py
stardive/instrumentation/__init__.py
stardive/instrumentation/api.py
stardive/instrumentation/context.py
stardive/lineage/__init__.py
stardive/lineage/graph.py
stardive/lineage/nodes.py
stardive/lineage/queries.py
stardive/lineage/validation.py
stardive/models/__init__.py
stardive/models/artifacts.py
stardive/models/attestations.py
stardive/models/builders.py
stardive/models/enums.py
stardive/models/events.py
stardive/models/identity.py
stardive/models/policy.py
stardive/models/run_plan.py
stardive/models/run_record.py
stardive/models/steps.py
stardive/replay/__init__.py
stardive/replay/attestation.py
stardive/replay/diff.py
stardive/replay/snapshot_view.py
stardive/replay/verification.py
stardive/sdk/__init__.py
stardive/sdk/context.py
stardive/sdk/handles.py
stardive/sdk/models.py
stardive/sdk/registry.py
stardive/storage/__init__.py
stardive/storage/base.py
stardive/storage/sqlite.py
stardive-0.1.0a2.dist-info/METADATA
stardive-0.1.0a2.dist-info/WHEEL
stardive-0.1.0a2.dist-info/licenses/LICENSE
stardive-0.1.0a2.dist-info/RECORD
