Metadata-Version: 2.4
Name: stardive
Version: 0.1.0a2
Summary: Audit-grade execution kernel for AI workflows - immutable trails, artifact provenance, and replay capability
Project-URL: Homepage, https://stardive.xyz
Project-URL: Documentation, https://github.com/StarDiveAI/stardive-core/docs
Project-URL: Repository, https://github.com/StarDiveAI/stardive-core
Project-URL: Source Code, https://github.com/StarDiveAI/stardive-core
Project-URL: Issues, https://github.com/StarDiveAI/stardive-core/issues
Project-URL: Bug Tracker, https://github.com/StarDiveAI/stardive-core/issues
Project-URL: Changelog, https://github.com/StarDiveAI/stardive-core/blob/main/CHANGELOG.md
Project-URL: Discussions, https://github.com/StarDiveAI/stardive-core/discussions
Author-email: Stardive Contributors <jiaye@stardive.xyz>
Maintainer-email: Stardive Contributors <jiaye@stardive.xyz>
License: AGPL-3.0-or-later
License-File: LICENSE
Keywords: agents,ai,audit,compliance,governance,immutable,lineage,llm,observability,provenance,regulated-ai,replay,workflow
Classifier: Development Status :: 3 - Alpha
Classifier: Intended Audience :: Developers
Classifier: Intended Audience :: Financial and Insurance Industry
Classifier: Intended Audience :: Healthcare Industry
Classifier: Intended Audience :: Legal Industry
Classifier: License :: OSI Approved :: GNU Affero General Public License v3 or later (AGPLv3+)
Classifier: Operating System :: OS Independent
Classifier: Programming Language :: Python :: 3
Classifier: Programming Language :: Python :: 3 :: Only
Classifier: Programming Language :: Python :: 3.10
Classifier: Programming Language :: Python :: 3.11
Classifier: Programming Language :: Python :: 3.12
Classifier: Topic :: Scientific/Engineering :: Artificial Intelligence
Classifier: Topic :: Software Development :: Libraries :: Python Modules
Classifier: Topic :: System :: Logging
Classifier: Topic :: System :: Monitoring
Classifier: Typing :: Typed
Requires-Python: >=3.10
Requires-Dist: click>=8.1.0
Requires-Dist: fastapi>=0.110.0
Requires-Dist: httpx>=0.27.0
Requires-Dist: pip>=25.3
Requires-Dist: pydantic>=2.0.0
Requires-Dist: pyyaml>=6.0
Requires-Dist: rich>=13.0.0
Requires-Dist: uvicorn>=0.30.0
Provides-Extra: dev
Requires-Dist: black>=23.0.0; extra == 'dev'
Requires-Dist: mypy>=1.0.0; extra == 'dev'
Requires-Dist: pytest-asyncio>=0.21.0; extra == 'dev'
Requires-Dist: pytest-cov>=4.0.0; extra == 'dev'
Requires-Dist: pytest>=7.0.0; extra == 'dev'
Requires-Dist: ruff>=0.1.0; extra == 'dev'
